coinmetrics/__init__.py
coinmetrics/base.py
coinmetrics/community.py
coinmetrics/errors.py
coinmetrics/utils.py
coinmetrics-0.2.5.dist-info/METADATA
coinmetrics-0.2.5.dist-info/WHEEL
coinmetrics-0.2.5.dist-info/top_level.txt
coinmetrics-0.2.5.dist-info/RECORD
