Metadata-Version: 2.1
Name: coinmetrics
Version: 0.2.5
Summary: An unofficial library to standardize queries to the Coin Metrics (coinmetrics.io) API.
Home-page: https://github.com/h4110w33n/coinmetrics
Author: Robert Rice
Author-email: h4110w33n@gmail.com
License: GNU General Public License v3 (GPLv3)
Keywords: coinmetrics,crypto,cryptocurrency,rest,api
Platform: UNKNOWN
Classifier: Development Status :: 5 - Production/Stable
Classifier: Intended Audience :: Developers
Classifier: Intended Audience :: Education
Classifier: Intended Audience :: Financial and Insurance Industry
Classifier: Intended Audience :: Information Technology
Classifier: License :: OSI Approved :: GNU General Public License v3 (GPLv3)
Classifier: Operating System :: OS Independent
Classifier: Programming Language :: Python :: 3.3
Classifier: Programming Language :: Python :: 3.4
Classifier: Programming Language :: Python :: 3.5
Classifier: Programming Language :: Python :: 3.6
Classifier: Programming Language :: Python :: 3.7
Classifier: Programming Language :: Python
Classifier: Topic :: Internet :: WWW/HTTP :: Indexing/Search
Classifier: Topic :: Scientific/Engineering :: Information Analysis
Classifier: Topic :: Scientific/Engineering :: Mathematics
Classifier: Topic :: Software Development :: Libraries :: Python Modules
Provides: coinmetrics
Requires-Dist: certifi
Requires-Dist: chardet
Requires-Dist: idna
Requires-Dist: python-dateutil
Requires-Dist: requests
Requires-Dist: six
Requires-Dist: urllib3
Requires-Dist: setuptools
